ohms_law_ksu/__init__.py
ohms_law_ksu/calc.py
ohms_law_ksu-0.3.0.dist-info/licenses/LICENSE
ohms_law_ksu-0.3.0.dist-info/METADATA
ohms_law_ksu-0.3.0.dist-info/WHEEL
ohms_law_ksu-0.3.0.dist-info/top_level.txt
ohms_law_ksu-0.3.0.dist-info/RECORD
